{
  "lastUpdate": "2025-11-27T17:34:09.575Z",
  "cetus": {
    "location": "cetus",
    "currentState": "night",
    "lastCheck": "2025-11-27T17:34:09.575Z",
    "expiry": "2025-11-27T18:11:40.428Z"
  },
  "vallis": {
    "location": "vallis",
    "currentState": "day",
    "lastCheck": "2025-11-27T17:34:09.575Z",
    "expiry": "2025-11-27T17:40:24.000Z"
  },
  "earth": {
    "location": "earth",
    "currentState": "night",
    "lastCheck": "2025-11-27T17:34:09.575Z",
    "expiry": "2025-11-27T18:11:40.428Z"
  },
  "cambion": {
    "location": "cambion",
    "currentState": "day",
    "lastCheck": "2025-11-27T17:34:09.575Z",
    "expiry": "2025-11-27T17:50:00.000Z"
  }
}